{
  "base_year": "2012=100",
  "months": [
    "2023-07",
    "2023-08",
    "2023-09",
    "2023-10",
    "2023-11",
    "2023-12",
    "2024-01",
    "2024-02",
    "2024-03",
    "2024-04",
    "2024-05",
    "2024-06",
    "2024-07",
    "2024-08",
    "2024-09",
    "2024-10",
    "2024-11",
    "2024-12",
    "2025-01",
    "2025-02",
    "2025-03",
    "2025-04",
    "2025-05",
    "2025-06",
    "2025-07",
    "2025-08",
    "2025-09",
    "2025-10",
    "2025-11",
    "2025-12",
    "2026-01",
    "2026-02",
    "2026-03",
    "2026-04",
    "2026-05",
    "2026-06"
  ],
  "categories": {
    "food_beverages": {
      "label": "Food & beverages",
      "index_urban": [
        153.0,
        152.7,
        152.84,
        152.89,
        153.87,
        154.74,
        155.99,
        155.8,
        156.21,
        155.91,
        159.46,
        158.52,
        156.21,
        156.22,
        157.04,
        157.67,
        157.72,
        158.43,
        159.54,
        159.2,
        160.3,
        161.2,
        161.47,
        161.4,
        162.77,
        163.03,
        162.84,
        162.67,
        163.84,
        164.58,
        165.68,
        166.65,
        167.26,
        168.66,
        168.99,
        169.64
      ],
      "index_rural": [
        150.84,
        150.96,
        150.62,
        151.24,
        151.96,
        154.15,
        155.03,
        154.72,
        155.55,
        154.94,
        158.76,
        157.46,
        154.44,
        154.99,
        155.8,
        156.75,
        156.69,
        156.06,
        157.74,
        157.48,
        159.46,
        159.24,
        160.64,
        160.14,
        160.29,
        161.25,
        161.23,
        160.8,
        161.65,
        162.53,
        164.72,
        166.09,
        166.13,
        167.62,
        168.07,
        167.25
      ]
    },
    "housing": {
      "label": "Housing",
      "index_urban": [
        155.98,
        156.21,
        156.66,
        156.95,
        157.54,
        157.87,
        158.08,
        158.28,
        158.66,
        158.87,
        159.27,
        159.86,
        160.15,
        160.33,
        160.98,
        161.34,
        161.44,
        161.52,
        161.63,
        162.06,
        162.59,
        162.89,
        162.98,
        163.26,
        163.9,
        164.27,
        164.9,
        165.47,
        165.53,
        166.01,
        166.47,
        166.84,
        167.05,
        167.49,
        167.6,
        167.91
      ],
      "index_rural": [
        154.57,
        153.8,
        154.41,
        155.92,
        156.04,
        157.01,
        155.75,
        156.04,
        157.56,
        157.09,
        157.55,
        159.05,
        158.12,
        158.75,
        158.92,
        159.78,
        160.94,
        160.37,
        161.09,
        159.7,
        160.33,
        160.73,
        161.86,
        162.64,
        161.64,
        161.88,
        164.23,
        164.0,
        164.89,
        163.99,
        164.44,
        166.08,
        165.6,
        165.89,
        166.57,
        165.67
      ]
    },
    "fuel_light": {
      "label": "Fuel & light",
      "index_urban": [
        164.28,
        163.78,
        164.19,
        165.13,
        164.59,
        164.37,
        171.05,
        166.77,
        166.9,
        167.25,
        166.49,
        166.02,
        165.86,
        166.41,
        165.96,
        165.47,
        164.57,
        165.24,
        164.78,
        166.21,
        171.52,
        166.62,
        166.19,
        166.96,
        166.46,
        165.73,
        167.25,
        167.75,
        167.97,
        169.07,
        170.23,
        169.66,
        168.83,
        168.94,
        169.03,
        169.23
      ],
      "index_rural": [
        162.32,
        161.93,
        161.72,
        164.43,
        163.28,
        163.19,
        168.83,
        165.77,
        166.02,
        165.85,
        165.15,
        164.96,
        164.86,
        164.06,
        164.57,
        163.25,
        162.97,
        164.64,
        162.28,
        164.04,
        169.08,
        164.27,
        163.99,
        166.13,
        164.99,
        164.8,
        165.95,
        167.13,
        166.71,
        166.6,
        169.2,
        167.59,
        167.42,
        167.59,
        166.62,
        166.74
      ]
    },
    "clothing": {
      "label": "Clothing",
      "index_urban": [
        148.23,
        148.64,
        148.72,
        148.88,
        149.44,
        149.76,
        150.07,
        150.5,
        150.51,
        150.84,
        151.12,
        151.62,
        151.69,
        152.25,
        152.28,
        152.37,
        152.7,
        153.09,
        153.21,
        153.26,
        153.78,
        153.9,
        154.24,
        154.59,
        154.82,
        155.15,
        155.45,
        155.99,
        156.09,
        156.5,
        156.62,
        156.84,
        157.22,
        157.38,
        157.55,
        157.99
      ],
      "index_rural": [
        147.58,
        147.22,
        146.22,
        146.39,
        148.79,
        148.83,
        149.04,
        148.13,
        148.25,
        148.58,
        149.88,
        150.8,
        149.52,
        150.34,
        150.56,
        149.9,
        150.89,
        152.57,
        151.08,
        152.16,
        151.95,
        151.52,
        153.47,
        153.86,
        154.11,
        153.54,
        154.41,
        154.28,
        154.15,
        155.59,
        154.85,
        155.81,
        155.74,
        155.07,
        155.36,
        157.31
      ]
    },
    "transport": {
      "label": "Transport",
      "index_urban": [
        153.68,
        153.64,
        153.17,
        153.92,
        154.46,
        154.4,
        155.1,
        155.51,
        155.71,
        155.25,
        154.89,
        155.82,
        156.79,
        157.18,
        158.03,
        158.49,
        158.24,
        157.97,
        157.98,
        158.94,
        159.73,
        160.63,
        161.59,
        161.44,
        161.36,
        161.05,
        161.82,
        162.75,
        162.92,
        163.43,
        163.2,
        164.21,
        165.11,
        166.19,
        167.01,
        167.94
      ],
      "index_rural": [
        153.13,
        151.67,
        152.01,
        151.56,
        152.36,
        152.17,
        152.98,
        154.48,
        153.64,
        154.53,
        152.65,
        153.6,
        155.85,
        155.05,
        156.61,
        157.38,
        156.15,
        157.01,
        157.43,
        158.05,
        158.57,
        158.4,
        159.16,
        160.38,
        159.58,
        159.75,
        159.36,
        161.18,
        160.54,
        162.7,
        160.76,
        163.35,
        162.68,
        165.16,
        166.29,
        166.57
      ]
    },
    "healthcare": {
      "label": "Healthcare",
      "index_urban": [
        156.18,
        156.43,
        156.92,
        157.33,
        157.64,
        158.1,
        158.3,
        158.87,
        158.87,
        159.61,
        160.04,
        160.62,
        161.21,
        161.75,
        162.04,
        162.09,
        162.63,
        162.89,
        163.14,
        163.82,
        164.39,
        164.63,
        164.88,
        165.21,
        165.53,
        165.77,
        165.87,
        166.21,
        166.96,
        167.5,
        168.22,
        168.71,
        168.96,
        169.39,
        169.39,
        169.62
      ],
      "index_rural": [
        154.82,
        154.77,
        155.11,
        155.9,
        156.26,
        157.17,
        156.85,
        156.57,
        156.78,
        158.77,
        159.37,
        159.09,
        159.44,
        160.58,
        159.9,
        160.09,
        160.78,
        161.94,
        162.24,
        163.27,
        163.4,
        163.18,
        162.68,
        164.56,
        164.2,
        164.01,
        164.98,
        164.32,
        165.47,
        166.51,
        166.41,
        168.2,
        166.96,
        167.35,
        168.68,
        168.27
      ]
    },
    "education": {
      "label": "Education",
      "index_urban": [
        158.17,
        158.77,
        159.2,
        159.44,
        159.76,
        160.32,
        160.72,
        161.26,
        161.75,
        162.37,
        162.82,
        163.42,
        164.0,
        164.46,
        164.97,
        165.39,
        165.95,
        166.39,
        166.96,
        167.48,
        167.89,
        168.22,
        168.53,
        169.01,
        169.54,
        169.96,
        170.44,
        170.77,
        171.02,
        171.35,
        171.68,
        172.03,
        172.46,
        172.74,
        173.05,
        173.55
      ],
      "index_rural": [
        156.26,
        158.14,
        157.88,
        157.85,
        158.43,
        159.41,
        159.38,
        158.95,
        160.08,
        160.48,
        160.61,
        161.39,
        162.74,
        163.95,
        163.77,
        163.38,
        163.74,
        163.98,
        165.62,
        165.48,
        166.3,
        166.51,
        167.59,
        168.07,
        168.17,
        169.4,
        169.27,
        168.91,
        169.71,
        170.52,
        170.25,
        171.27,
        170.72,
        172.19,
        171.76,
        171.92
      ]
    },
    "misc": {
      "label": "Miscellaneous goods & services",
      "index_urban": [
        153.98,
        154.45,
        154.42,
        154.71,
        154.59,
        154.8,
        154.84,
        155.0,
        155.59,
        155.8,
        156.38,
        157.04,
        157.12,
        157.03,
        156.88,
        157.25,
        158.08,
        158.26,
        158.74,
        159.35,
        159.84,
        160.42,
        161.2,
        161.23,
        161.08,
        161.06,
        161.02,
        161.52,
        161.91,
        161.96,
        162.49,
        163.09,
        163.08,
        163.52,
        164.1,
        164.04
      ],
      "index_rural": [
        151.84,
        152.02,
        153.7,
        154.16,
        153.47,
        152.95,
        152.42,
        153.71,
        153.66,
        155.15,
        154.5,
        155.29,
        156.42,
        154.99,
        154.68,
        155.55,
        157.34,
        155.79,
        156.67,
        158.16,
        158.48,
        159.18,
        159.69,
        160.05,
        158.88,
        158.92,
        160.31,
        159.1,
        160.14,
        159.8,
        160.58,
        161.72,
        161.11,
        161.09,
        163.06,
        161.92
      ]
    }
  },
  "headline": {
    "index_urban": [
      154.53,
      154.54,
      154.68,
      154.97,
      155.46,
      155.91,
      157.07,
      156.82,
      157.18,
      157.2,
      158.7,
      158.64,
      157.92,
      158.09,
      158.52,
      158.89,
      159.06,
      159.46,
      160.01,
      160.29,
      161.43,
      161.64,
      161.99,
      162.11,
      162.69,
      162.79,
      163.0,
      163.27,
      163.9,
      164.45,
      165.15,
      165.77,
      166.1,
      166.91,
      167.26,
      167.69
    ],
    "index_rural": [
      152.75,
      152.66,
      152.84,
      153.55,
      153.9,
      154.83,
      155.46,
      155.39,
      155.88,
      156.08,
      157.41,
      157.33,
      156.44,
      156.5,
      156.92,
      157.44,
      157.85,
      157.66,
      158.38,
      158.73,
      160.1,
      159.75,
      160.68,
      161.06,
      160.65,
      161.06,
      161.7,
      161.48,
      162.09,
      162.64,
      163.66,
      164.87,
      164.55,
      165.42,
      166.12,
      165.64
    ]
  },
  "weights": {
    "food_beverages": 0.39,
    "housing": 0.1,
    "fuel_light": 0.08,
    "clothing": 0.065,
    "transport": 0.084,
    "healthcare": 0.059,
    "education": 0.042,
    "misc": 0.18
  }
}